pdforge/__init__.py
pdforge/__main__.py
pdforge/_utils.py
pdforge/cat.py
pdforge/cli.py
pdforge/extract_images.py
pdforge/extract_text.py
pdforge/meta.py
pdforge/parsing.py
pdforge/rm.py
pdforge/rotate.py
pdforge/secure.py
pdforge/watermark.py
pdforge-0.1.0.dist-info/METADATA
pdforge-0.1.0.dist-info/WHEEL
pdforge-0.1.0.dist-info/entry_points.txt
pdforge-0.1.0.dist-info/licenses/LICENSE
pdforge-0.1.0.dist-info/RECORD
