Metadata-Version: 2.4
Name: pdforge
Version: 0.1.0
Summary: A command-line utility for modifying PDFs with ease. Perform common PDF operations such as merging, splitting, compressing, and extracting pages, all from your terminal.
Project-URL: Homepage, https://github.com/victormhp/pdforge
Project-URL: Issues, https://github.com/victormhp/pdforge/issues
Author-email: Victor Alberto <victoralbertomhp@gmail.com>
License-Expression: MIT
License-File: LICENSE
Classifier: Development Status :: 4 - Beta
Classifier: Programming Language :: Python :: 3.11
Classifier: Programming Language :: Python :: 3.12
Requires-Python: >=3.11
Requires-Dist: pymupdf>=1.25.3
